colornames.py
pycolornames-1.1.0.dist-info/LICENSE
pycolornames-1.1.0.dist-info/METADATA
pycolornames-1.1.0.dist-info/WHEEL
pycolornames-1.1.0.dist-info/top_level.txt
pycolornames-1.1.0.dist-info/RECORD
