Metadata-Version: 2.1
Name: pycolornames
Version: 1.1.0
Summary: Finds the name of any color.
Author-email: Robin Gustafsson <robin@rgson.se>
License: MIT License
Project-URL: Homepage, https://github.com/rgson/python-colornames
Project-URL: Issues, https://github.com/rgson/python-colornames/issues
Project-URL: Repository, https://github.com/rgson/python-colornames.git
Classifier: Programming Language :: Python :: 3
Classifier: License :: OSI Approved :: MIT License
Classifier: Operating System :: OS Independent
Requires-Python: >=3.4
License-File: LICENSE
